pbpstatsapi/__init__.py
pbpstatsapi/api.py
pbpstatsapi-1.0.2.dist-info/METADATA
pbpstatsapi-1.0.2.dist-info/WHEEL
pbpstatsapi-1.0.2.dist-info/licenses/LICENSE
pbpstatsapi-1.0.2.dist-info/RECORD
