Metadata-Version: 2.1
Name: pbpstatsapi
Version: 1.0.2
Summary: A Python wrapper around some requests to the PBP Stats API
Project-URL: Homepage, https://github.com/MidpriceDog/pbp-stats-client
Project-URL: Bug Tracker, https://github.com/MidpriceDog/pbp-stats-client/issues
Author: MidpriceDog
License-File: LICENSE
Classifier: License :: OSI Approved :: MIT License
Classifier: Operating System :: OS Independent
Classifier: Programming Language :: Python :: 3
Requires-Python: >=3.7
